windfreak/__init__.py
windfreak/device.py
windfreak/synth_hd.py
windfreak-0.3.0.dist-info/METADATA
windfreak-0.3.0.dist-info/WHEEL
windfreak-0.3.0.dist-info/top_level.txt
windfreak-0.3.0.dist-info/RECORD
