Metadata-Version: 2.1
Name: windfreak
Version: 0.3.0
Summary: Python package for Windfreak Technologies devices.
Home-page: https://github.com/christian-hahn/windfreak-python
Author: Christian Hahn
Author-email: christianhahn09@gmail.com
License: MIT
Platform: UNKNOWN
Classifier: Programming Language :: Python :: 3
Classifier: License :: OSI Approved :: MIT License
Classifier: Operating System :: OS Independent
Requires-Python: >=3
Requires-Dist: pyserial
